{
  "symbol": "PFL",
  "comparison_date": "2025-12-01T12:53:06.832906",
  "horizons": [
    1,
    3,
    5,
    10,
    15,
    21
  ],
  "lstm": {
    "symbol": "PFL",
    "horizons": {
      "1": {
        "predicted_price": 382.07,
        "predicted_return": -0.5026041666666685,
        "mape": 0.5026041666666685,
        "mae": 0.08747679837555143,
        "direction_accuracy": 0.0,
        "rmse": 0.0,
        "r2": 0.0
      },
      "3": {
        "predicted_price": 356.74,
        "predicted_return": -7.098958333333331,
        "mape": 7.098958333333331,
        "mae": 0.06876323014232656,
        "direction_accuracy": 0.0,
        "rmse": 0.0,
        "r2": 0.0
      },
      "5": {
        "predicted_price": 432.34,
        "predicted_return": 12.58854166666666,
        "mape": 12.58854166666666,
        "mae": 0.06467180998880147,
        "direction_accuracy": 0.0,
        "rmse": 0.0,
        "r2": 0.0
      },
      "10": {
        "predicted_price": 286.605,
        "predicted_return": -25.363281249999996,
        "mape": 25.363281249999996,
        "mae": 0.09589407158439343,
        "direction_accuracy": 0.0,
        "rmse": 0.0,
        "r2": 0.0
      },
      "15": {
        "predicted_price": 178.93999999999994,
        "predicted_return": -53.401041666666686,
        "mape": 53.401041666666686,
        "mae": 0.10484720989229658,
        "direction_accuracy": 0.0,
        "rmse": 0.0,
        "r2": 0.0
      },
      "21": {
        "predicted_price": 381.29,
        "predicted_return": -0.7057291666666614,
        "mape": 0.7057291666666614,
        "mae": 0.035535645279780315,
        "direction_accuracy": 0.0,
        "rmse": 0.0,
        "r2": 0.0
      }
    },
    "training_time": 143.10513305664062
  },
  "xlstm": {
    "symbol": "PFL",
    "training_time": 193.53357195854187,
    "parameters": 12485238,
    "horizons": {
      "1": {
        "mae": 6.157167846812895,
        "mape": 1.5849680483809419,
        "rmse": 8.91380363081856,
        "r2": 0.004197063456571781,
        "mae_returns": 0.01603429054093716,
        "predicted_price": 383.8348361849785,
        "predicted_return": -0.04301141016185284
      },
      "3": {
        "mae": 9.740977024759195,
        "mape": 2.4816113062792464,
        "rmse": 14.6950617570349,
        "r2": 0.04892816175628267,
        "mae_returns": 0.025367127655742196,
        "predicted_price": 383.89118814468384,
        "predicted_return": -0.02833642065525055
      },
      "5": {
        "mae": 13.050768818178327,
        "mape": 3.3518420336761725,
        "rmse": 17.437417420592777,
        "r2": 0.04037401707788624,
        "mae_returns": 0.033986379028001466,
        "predicted_price": 384.80552700161934,
        "predicted_return": 0.20977265667170286
      },
      "10": {
        "mae": 15.198408249201046,
        "mape": 3.9675751137219986,
        "rmse": 19.74305674046948,
        "r2": 0.0031232304127400967,
        "mae_returns": 0.039579185399273645,
        "predicted_price": 384.57373210787773,
        "predicted_return": 0.1494094030931592
      },
      "15": {
        "mae": 18.066763413635957,
        "mape": 4.788806662047338,
        "rmse": 21.908080158982777,
        "r2": -0.03954174010859157,
        "mae_returns": 0.04704886254303557,
        "predicted_price": 385.40126100182533,
        "predicted_return": 0.36491171922534704
      },
      "21": {
        "mae": 20.283614466571468,
        "mape": 5.481434672132237,
        "rmse": 24.62089760001018,
        "r2": -0.15682071667561281,
        "mae_returns": 0.052821902414078754,
        "predicted_price": 386.3142018914223,
        "predicted_return": 0.6026567425578833
      }
    }
  }
}